HamlPy3-0.84.0.dist-info/DESCRIPTION.rst
HamlPy3-0.84.0.dist-info/METADATA
HamlPy3-0.84.0.dist-info/RECORD
HamlPy3-0.84.0.dist-info/WHEEL
HamlPy3-0.84.0.dist-info/entry_points.txt
HamlPy3-0.84.0.dist-info/metadata.json
HamlPy3-0.84.0.dist-info/top_level.txt
hamlpy/__init__.py
hamlpy/elements.py
hamlpy/ext.py
hamlpy/hamlpy.py
hamlpy/hamlpy_watcher.py
hamlpy/nodes.py
hamlpy/templatize.py
hamlpy/template/__init__.py
hamlpy/template/loaders.py
hamlpy/template/utils.py
