Metadata-Version: 2.0
Name: HamlPy3
Version: 0.84.0
Summary: A python 3 fork & drop-in replacement of HamlPy. HAML like syntax for Django templates
Home-page: http://github.com/appknox/HamlPy3
Author: dhilipsiva
Author-email: dhilipsiva@gmail.com
License: MIT
Keywords: haml django converter
Platform: UNKNOWN
Classifier: Development Status :: 4 - Beta
Classifier: Intended Audience :: Developers
Classifier: Topic :: Software Development :: Libraries
Classifier: License :: OSI Approved :: MIT License
Classifier: Programming Language :: Python :: 3
Classifier: Programming Language :: Python :: 3.5
